bmp_sensors/BME280.py
bmp_sensors/BME680.py
bmp_sensors/BMP085.py
bmp_sensors/BMP180.py
bmp_sensors/BMP280.py
bmp_sensors/__init__.py
bmp_sensors-1.1.3.dist-info/LICENSE
bmp_sensors-1.1.3.dist-info/METADATA
bmp_sensors-1.1.3.dist-info/WHEEL
bmp_sensors-1.1.3.dist-info/top_level.txt
bmp_sensors-1.1.3.dist-info/RECORD
