Metadata-Version: 2.1
Name: bmp-sensors
Version: 1.1.3
Summary: I2C driver for the Bosch Sensortec BMP-Sensors family.
Home-page: https://gitlab.com/Kampi/bmp-sensors
Author: Daniel Kampert
Author-email: DanielKampert@kampis-elektroecke.de
License: UNKNOWN
Platform: UNKNOWN
Classifier: Programming Language :: Python :: 3
Classifier: License :: OSI Approved :: GNU General Public License v3 (GPLv3)
Classifier: Operating System :: OS Independent
Requires-Python: >=3.0
Requires-Dist: smbus
